tldr.py
tldrcli-1.3.2.dist-info/licenses/LICENSE
tldrcli-1.3.2.dist-info/METADATA
tldrcli-1.3.2.dist-info/WHEEL
tldrcli-1.3.2.dist-info/entry_points.txt
tldrcli-1.3.2.dist-info/top_level.txt
tldrcli-1.3.2.dist-info/RECORD
