Metadata-Version: 2.4
Name: tldrcli
Version: 1.3.2
Summary: Your new CLI tool helping you learn and fix errors in Python fast!
Author: Devanshu Pandya
Author-email: pandyadevh@gmail.com
License-File: LICENSE
Requires-Dist: annotated-types>=0.7.0
Requires-Dist: anyio>=4.10.0
Requires-Dist: certifi>=2025.8.3
Requires-Dist: exceptiongroup>=1.3.0
Requires-Dist: h11>=0.16.0
Requires-Dist: httpcore>=1.0.9
Requires-Dist: httpx>=0.28.1
Requires-Dist: idna>=3.10
Requires-Dist: ollama>=0.5.3
Requires-Dist: pydantic>=2.11.7
Requires-Dist: pydantic_core>=2.33.2
Requires-Dist: sniffio>=1.3.1
Requires-Dist: tldr>=0.1
Requires-Dist: tldrcli>=0.1
Requires-Dist: typing-inspection>=0.4.1
Requires-Dist: typing_extensions>=4.14.1
Dynamic: author
Dynamic: author-email
Dynamic: description
Dynamic: description-content-type
Dynamic: license-file
Dynamic: requires-dist
Dynamic: summary
